clippy/Clipping.py
clippy/__init__.py
kindle_clippy-0.0.2.dist-info/licenses/LICENSE.txt
kindle_clippy-0.0.2.dist-info/METADATA
kindle_clippy-0.0.2.dist-info/WHEEL
kindle_clippy-0.0.2.dist-info/top_level.txt
kindle_clippy-0.0.2.dist-info/RECORD
