Metadata-Version: 2.4
Name: kindle_clippy
Version: 0.0.2
Summary: Clippy is a Python package for parsing Kindle's `My Clippings.txt` file.
Author: Scarlett Swerdlow
License-Expression: MIT
Project-URL: Homepage, https://github.com/scarlettswerdlow/clippy
Project-URL: Issues, https://github.com/scarlettswerdlow/clippy/issues
Classifier: Programming Language :: Python :: 3
Classifier: Operating System :: OS Independent
Requires-Python: >=3.8
License-File: LICENSE.txt
Dynamic: license-file
